ImageEnhancdQualityAccess/IQAEnhanceImage.py
ImageEnhancdQualityAccess/__init__.py
ImageEnhancdQualityAccess/ImageEnhance/ExposureFusion.py
ImageEnhancdQualityAccess/ImageEnhance/PixelLightArrange.py
ImageEnhancdQualityAccess/ImageEnhance/__init__.py
ImageEnhancdQualityAccess/ImageQulityAccess/IQASet.py
ImageEnhancdQualityAccess/ImageQulityAccess/__init__.py
EIQA-0.0.4.dist-info/LICENSE
EIQA-0.0.4.dist-info/METADATA
EIQA-0.0.4.dist-info/WHEEL
EIQA-0.0.4.dist-info/top_level.txt
EIQA-0.0.4.dist-info/RECORD
