Metadata-Version: 2.1
Name: EIQA
Version: 0.0.4
Summary: A small toolkit for image enhancement and quality assessment
Author-email: Luster <hangyang@lusterinc.com>
Classifier: Programming Language :: Python :: 3
Classifier: License :: OSI Approved :: GNU General Public License v3 (GPLv3)
Classifier: Operating System :: OS Independent
Classifier: Development Status :: 3 - Alpha
Classifier: Topic :: Scientific/Engineering :: Image Processing
Requires-Python: >=3.8
License-File: LICENSE
Requires-Dist: scikit-image ==0.21.0
Requires-Dist: Pillow ==9.4.0
Requires-Dist: json5 ==0.9.17
Requires-Dist: opencv-python ==4.8.1.78
Requires-Dist: numpy >=1.22.3
Requires-Dist: onnxruntime ==1.16.3
Requires-Dist: onnxruntime-gpu ==1.18.1
Requires-Dist: torchvision >=0.14.1
